{
  "subNodes": [
    {
      "idNum": 0,
      "orderNum": 0,
      "pcNode": true,
      "linkTo": 0,
      "ShowOnlyOnce": false,
      "NodeIsActive": true,
      "NodePortraitBitmap": "",
      "NodeNpcName": "",
      "NodeSound": "none",
      "conversationText": "root",
      "IsExpanded": true,
      "subNodes": [
        {
          "idNum": 1,
          "orderNum": 0,
          "pcNode": false,
          "linkTo": 0,
          "ShowOnlyOnce": false,
          "NodeIsActive": true,
          "NodePortraitBitmap": "forest.png",
          "NodeNpcName": "",
          "NodeSound": "none",
          "conversationText": "Finally. The path out winds ahead of you,  back to the village of Gildoen where you will find ale, food and a bed to sleep on.",
          "IsExpanded": true,
          "subNodes": [
            {
              "idNum": 2,
              "orderNum": 0,
              "pcNode": true,
              "linkTo": 0,
              "ShowOnlyOnce": false,
              "NodeIsActive": true,
              "NodePortraitBitmap": "",
              "NodeNpcName": "",
              "NodeSound": "none",
              "conversationText": "Continue.",
              "IsExpanded": true,
              "subNodes": [
                {
                  "idNum": 3,
                  "orderNum": 0,
                  "pcNode": false,
                  "linkTo": 0,
                  "ShowOnlyOnce": false,
                  "NodeIsActive": true,
                  "NodePortraitBitmap": "forest.png",
                  "NodeNpcName": "",
                  "NodeSound": "none",
                  "conversationText": "The birds are singing in the trees, and behind you the forest seems peaceful again. You have a spring in your step as you head down the path.",
                  "IsExpanded": true,
                  "subNodes": [
                    {
                      "idNum": 4,
                      "orderNum": 0,
                      "pcNode": true,
                      "linkTo": 0,
                      "ShowOnlyOnce": false,
                      "NodeIsActive": true,
                      "NodePortraitBitmap": "",
                      "NodeNpcName": "",
                      "NodeSound": "none",
                      "conversationText": "Continue.",
                      "IsExpanded": true,
                      "subNodes": [
                        {
                          "idNum": 5,
                          "orderNum": 0,
                          "pcNode": false,
                          "linkTo": 0,
                          "ShowOnlyOnce": false,
                          "NodeIsActive": true,
                          "NodePortraitBitmap": "forest2.png",
                          "NodeNpcName": "",
                          "NodeSound": "none",
                          "conversationText": "Holy shit!",
                          "IsExpanded": true,
                          "subNodes": [
                            {
                              "idNum": 6,
                              "orderNum": 0,
                              "pcNode": true,
                              "linkTo": 0,
                              "ShowOnlyOnce": false,
                              "NodeIsActive": true,
                              "NodePortraitBitmap": "",
                              "NodeNpcName": "",
                              "NodeSound": "none",
                              "conversationText": "Continue.",
                              "IsExpanded": true,
                              "subNodes": [
                                {
                                  "idNum": 7,
                                  "orderNum": 0,
                                  "pcNode": false,
                                  "linkTo": 0,
                                  "ShowOnlyOnce": false,
                                  "NodeIsActive": true,
                                  "NodePortraitBitmap": "",
                                  "NodeNpcName": "",
                                  "NodeSound": "none",
                                  "conversationText": "Its a troll! Again!",
                                  "IsExpanded": true,
                                  "subNodes": [
                                    {
                                      "idNum": 8,
                                      "orderNum": 0,
                                      "pcNode": true,
                                      "linkTo": 0,
                                      "ShowOnlyOnce": false,
                                      "NodeIsActive": true,
                                      "NodePortraitBitmap": "",
                                      "NodeNpcName": "",
                                      "NodeSound": "none",
                                      "conversationText": "Continue.",
                                      "IsExpanded": true,
                                      "subNodes": [
                                        {
                                          "idNum": 9,
                                          "orderNum": 0,
                                          "pcNode": false,
                                          "linkTo": 0,
                                          "ShowOnlyOnce": false,
                                          "NodeIsActive": true,
                                          "NodePortraitBitmap": "",
                                          "NodeNpcName": "",
                                          "NodeSound": "none",
                                          "conversationText": "The troll speaks in its raw, raspy voice. \"Human! Human! I haven't forgotten you human!\".",
                                          "IsExpanded": true,
                                          "subNodes": [
                                            {
                                              "idNum": 11,
                                              "orderNum": 0,
                                              "pcNode": true,
                                              "linkTo": 0,
                                              "ShowOnlyOnce": false,
                                              "NodeIsActive": true,
                                              "NodePortraitBitmap": "",
                                              "NodeNpcName": "",
                                              "NodeSound": "none",
                                              "conversationText": "Continue.",
                                              "IsExpanded": true,
                                              "subNodes": [
                                                {
                                                  "idNum": 12,
                                                  "orderNum": 0,
                                                  "pcNode": false,
                                                  "linkTo": 0,
                                                  "ShowOnlyOnce": false,
                                                  "NodeIsActive": true,
                                                  "NodePortraitBitmap": "",
                                                  "NodeNpcName": "",
                                                  "NodeSound": "none",
                                                  "conversationText": "Bugger.",
                                                  "IsExpanded": true,
                                                  "subNodes": [
                                                    {
                                                      "idNum": 13,
                                                      "orderNum": 0,
                                                      "pcNode": true,
                                                      "linkTo": 0,
                                                      "ShowOnlyOnce": false,
                                                      "NodeIsActive": true,
                                                      "NodePortraitBitmap": "",
                                                      "NodeNpcName": "",
                                                      "NodeSound": "none",
                                                      "conversationText": "Continue.",
                                                      "IsExpanded": true,
                                                      "subNodes": [],
                                                      "actions": [],
                                                      "conditions": [],
                                                      "isLink": false
                                                    }
                                                  ],
                                                  "actions": [],
                                                  "conditions": [],
                                                  "isLink": false
                                                }
                                              ],
                                              "actions": [],
                                              "conditions": [],
                                              "isLink": false
                                            }
                                          ],
                                          "actions": [],
                                          "conditions": [],
                                          "isLink": false
                                        }
                                      ],
                                      "actions": [],
                                      "conditions": [],
                                      "isLink": false
                                    }
                                  ],
                                  "actions": [],
                                  "conditions": [],
                                  "isLink": false
                                }
                              ],
                              "actions": [],
                              "conditions": [],
                              "isLink": false
                            }
                          ],
                          "actions": [],
                          "conditions": [],
                          "isLink": false
                        }
                      ],
                      "actions": [],
                      "conditions": [],
                      "isLink": false
                    }
                  ],
                  "actions": [],
                  "conditions": [],
                  "isLink": false
                }
              ],
              "actions": [],
              "conditions": [],
              "isLink": false
            }
          ],
          "actions": [],
          "conditions": [],
          "isLink": false
        }
      ],
      "actions": [],
      "conditions": [],
      "isLink": false
    }
  ],
  "ConvoFileName": "Leavingraventhal",
  "Narration": true,
  "PartyChat": false,
  "SpeakToMainPcOnly": false,
  "NpcPortraitBitmap": "forest2.png",
  "DefaultNpcName": "",
  "NextIdNum": 0
}