{
  "tokenFilename": "tkn_snowball",
  "portraitFilename": "ptr_snowball",
  "combatFacingLeft": true,
  "combatFacing": 4,
  "combatLocX": 0,
  "combatLocY": 0,
  "moveDistance": 5,
  "knownSpellsTags": [],
  "knownSpellsList": [],
  "knownTraitsTags": [
    "cleave",
    "twoAttack"
  ],
  "knownTraitsList": [],
  "effectsList": [],
  "charStatus": "Alive",
  "fortitude": 0,
  "will": 0,
  "reflex": 0,
  "strength": 10,
  "dexterity": 10,
  "intelligence": 10,
  "charisma": 10,
  "constitution": 10,
  "wisdom": 10,
  "AC": 10,
  "classBonus": 0,
  "baseAttBonus": 1,
  "baseAttBonusAdders": 0,
  "hp": 65,
  "hpMax": 65,
  "sp": 50,
  "spMax": 50,
  "XPNeeded": 200,
  "hpRegenTimePassedCounter": 0,
  "spRegenTimePassedCounter": 0,
  "HeadRefs": {
    "resref": "none",
    "tag": "none",
    "name": "none",
    "canNotBeUnequipped": false,
    "quantity": 1
  },
  "NeckRefs": {
    "resref": "none",
    "tag": "none",
    "name": "none",
    "canNotBeUnequipped": false,
    "quantity": 1
  },
  "BodyRefs": {
    "resref": "chainmail",
    "tag": "chainmail_10924",
    "name": "Chainmail Armor",
    "canNotBeUnequipped": false,
    "quantity": 1
  },
  "MainHandRefs": {
    "resref": "lsword01",
    "tag": "lsword01_10937",
    "name": "Long Sword",
    "canNotBeUnequipped": false,
    "quantity": 1
  },
  "OffHandRefs": {
    "resref": "largeshield",
    "tag": "largeshield_10946",
    "name": "Large Shield",
    "canNotBeUnequipped": false,
    "quantity": 1
  },
  "RingRefs": {
    "resref": "none",
    "tag": "none",
    "name": "none",
    "canNotBeUnequipped": false,
    "quantity": 1
  },
  "Ring2Refs": {
    "resref": "none",
    "tag": "none",
    "name": "none",
    "canNotBeUnequipped": false,
    "quantity": 1
  },
  "FeetRefs": {
    "resref": "none",
    "tag": "none",
    "name": "none",
    "canNotBeUnequipped": false,
    "quantity": 1
  },
  "AmmoRefs": {
    "resref": "none",
    "tag": "none",
    "name": "none",
    "canNotBeUnequipped": false,
    "quantity": 1
  },
  "damageTypeResistanceTotalAcid": 0,
  "damageTypeResistanceTotalCold": 0,
  "damageTypeResistanceTotalNormal": 0,
  "damageTypeResistanceTotalElectricity": 0,
  "damageTypeResistanceTotalFire": 0,
  "damageTypeResistanceTotalMagic": 0,
  "damageTypeResistanceTotalPoison": 0,
  "name": "Snowball",
  "tag": "snowball",
  "nonRemoveablePc": false,
  "raceTag": "human",
  "classTag": "fighter",
  "classLevel": 5,
  "isMale": true,
  "baseFortitude": 4,
  "baseWill": 2,
  "baseReflex": 2,
  "baseStr": 17,
  "baseDex": 15,
  "baseInt": 13,
  "baseCha": 14,
  "baseCon": 14,
  "baseWis": 15,
  "ACBase": 10,
  "XP": 1600
}